{
"campaign_wizard": "Naujoji kampanija vedlys",
"campaign_remove": "pašalinti",
"navCampaign": "Kampanija",
"navResources": "Ištekliai",
"navStation": "Radijo stotys",
"navScenes": "Siužetai",
"navSettings": "Nustatymai",
"navGoPro": "Eiti Pro `",
"navStudioPanel": "Už",
"freeBrackets": "(NEMOKAMAI",
"onehundredFree": "100% nemokamai",
"nintynine": "$ 99 per mėnesį (butas",
"navHelpPanel": "Padėti",
"navLogout": "Logout",
"saveConfig": "Sutaupyti",
"editScreenLayout": "redaguoti ekrano išdėstymas",
"liveChat": "Live Pokalbiai",
"dashboard": "Prietaisų skydas",
"editScreenLayoutTitle": "ekrano išdėstymas redaktorius",
"pushToTop": "Stumti į viršų",
"studioLite": "StudioLite",
"rememberMe": "Prisiminti mane",
"signin": "Registruotis",
"haveNiceDay": "Have a nice day :",
"selectCampaignName": "Pasirinkite kampanijos pavadinimą",
"screenOrientation": "Pasirinkite ekrano padėtį",
"screenResolution": "Pasirinkite ekrano skiriamąją gebą",
"screenLayout": "Pasirinkite ekrano išdėstymą",
"noTimelineSelected": "nėra laiko juostą pasirinktas",
"addContent": "Pridėti turinį",
"removeContent": "Pašalinti turinį",
"contentToAdd": "Pasirinkite naują turinį pridėti",
"components": "komponentai",
"resources": "ištekliai",
"scenes": "scenos",
"comingSoon": "netrukus ...",
"pleaseWait": "Prašome palaukti",
"removeStation": "pašalinti stotį",
"noStation": "Nėra SignagePlayer pakrautas ...",
"rightPackage": "Pasirinkite paketą, kuris jums tinka!",
"studioLiteFree": "StudioLite",
"simpleInterface": "paprasta naudoti sąsaja",
"campaignManager": "Kampanijos vadovas",
"timelineManagement": "Laiko valdymas",
"screenTemplates": "Ekrano šablonai",
"screenEditor": "Ekrano redaktorius",
"StationManager": "Stoties valdytojas",
"supportComponents": "Paramos 10 dalys",
"sceneEditor": "Scenos redaktorius (dar",
"filesVIF": "video vaizdai blykstė",
"tabletsPhones": "Paleisti tablečių ir telefonai",
"openSourceGithub": "Atviro kodo (GitHub",
"youAreHere": "Jūs esate čia",
"studioProFree": "StudioPro",
"higherLearningCurve": "Aukštasis mokymosi kreivė",
"professionalEditor": "Profesionalus redaktorius",
"channelManagement": "Kanalų valdymas",
"schedulerSequencer": "Tvarkaraštis / sekvenceris",
"richSceneEditor": "Turtingas scena redaktorius",
"supportMoreComponents": "Palaikymo daugiau komponentų",
"advanceStationManager": "Išankstinis stoties valdytojas",
"runDesktopWeb": "Veikia ant darbastalio ir interneto",
"muchMore": "ir daug daugiau ...",
"convert": "Konvertuoti",
"enterprise": "Įmonė",
"everythingFromLiteAndPro": "Viskas nuo Lite ir Pro",
"whiteLabel": "Balta etiketė / prekės ženklo",
"supportAllComponents": "Palaikymo visus komponentus",
"transitions": "Perėjimai / efektai",
"multiUserManagement": "Kelių vartotojų valdymas",
"advertisingManager": "Reklamos vadybininkas",
"accessControl": "Praėjimo kontrolė",
"unlimitedCloudStorage": "Neribotas debesys saugykla",
"phoneSupport": "Telefono pagalba",
"hardwareDiscounts": "Aparatūra nuolaidos",
"month": "mėnuo",
"subscribe": "Prenumeruoti",
"videoTutorial": "Video pamoka - išmokti naudotis StudioLite",
"watchNow": "Žiūrėti jį dabar",
"additionalLinks": "Papildomos nuorodos",
"studioLitePage": "StudioLite page",
"supportForum": "Palaikymas forumas",
"liveChatSupport": "Live Pokalbiai / Pagalba",
"openSource": "Atviro kodo",
"webinar": "Webinar",
"faq": "DUK",
"knowledgeBase": "Žinių bazė",
"selectNextChannel": "pasirinkite kitą kanalą",
"nextChannel": "Kitas kanalas",
"addFiles": "pridėti failus",
"logout": "logout",
"server": "Serveris:",
"businessId": "Verslo id:",
"username": "Vartotojo vardas:",
"password": "Slaptažodis",
"lenght": "Ilgis",
"randPlay": "Atsitiktinis atkūrimas",
"off": "nuo",
"on": "apie",
"resProps": "išteklių savybės",
"screenDivision": "Ekrano padalinimo",
"os": "Operacinės sistemos",
"airVersion": "ORO versija",
"playerVersion": "Žaidėjas versija",
"peakMemory": "Didžiausioji atmintis",
"totalMemory": "Bendra atmintis",
"running": "Veikia",
"watchdog": "Sarginis šuo",
"lastUpd": "Paskutinis upd",
"sendStationEvent": "Siųsti stoties įvykių",
"enterQRText": "QR Įveskite tekstą",
"hoursMinutesSeconds": "valandos / minutės / sekundės",
"comp": "Comp",
"style": "Stilius",
"aspectRatio": "Ekrano kraštinių santykis",
"volumeLevel": "Garso lygis",
"autoRewind": "Automatinis atsukimas",
"rssNewsSource": "RSS naujienos šaltinis",
"rssRefreash": "RSS atnaujinimo laikmatis (min.",
"rsscroll": "RSS slinkties kryptis",
"horizontalMode": "Horizontali režimas",
"verticalMode": "Vertikali režimas",
"scrollSpeed": "Pereikite greitis",
"slow": "Lėtai",
"medium": "Vidutinis",
"fast": "Greitai",
"font": "Šriftas",
"maintainAR": "Išlaikyti proporcijas",
"webAddr": "Interneto adresas",
"urlAddr": "URL adresas",
"labelText": "Etiketės tekstas",
"chooseFormat": "Pasirinkite formatą",
"showBgColor": "Fono spalva",
"ModalTitle": "Modalinis pavadinimas",
"someContent": "kai turinys",
"close": "Arti",
"saveChanges": "Išsaugoti pakeitimus",
"aboutUs": "Apie mus",
"firstName": "Vardas",
"lastName": "Pavardė",
"top": "viršus",
"left": "į kairę",
"width": "plotis",
"height": "aukštis",
"angle": "kampas",
"enterNewCompaignName": "Įveskite naują kampanijų vardą",
"timelineTitle": "Laiko Pavadinimas",
"enterResName": "Įveskite išteklių pavadinimas",
"eventName": "Renginio pavadinimas",
"EnterRSSLink": "Įveskite RSS nuorodos tekstą",
"enterText": "Įveskite tekstą čia",
"removeTimelineButtonToolTip": "pašalinti pasirinktą laiko juostą (viena turi egzistuoti",
"addButtonToolTip": "ADD3",
"removeButtonToolTip": "pašalinti padalinys",
"pushDivToTopButtonToolTip": "stumti padalijimą į viršų",
"pushDivToBottomButtonToolTip": "stumti padalinį apačioje",
"getNextDivButtonToolTip": "gauti kitą padalinį",
"unregRemoteStationButtonToolTip": "wyrejestruje nuotolinio stotį",
"bootBoxThemeReload": "Jums gali tekti iš naujo paleisti StudioLite kad pakeitimai įsigaliotų,",
"bootBoxRestartStations": "Perkraukite prijungtas stočių ir taikyti visą išsaugotą darbą?",
"bootBoxStudioLiteAcc": "Turite prisijungti su StudioLite sąskaitą, o ne Pro sąskaitos",
"bootBoxLoginWrongCred": "Jūs esate prisijungęs su NEMOKAMAI SignageStudio Pro įgaliojimų ne Laisvas StudioLite įgaliojimai taip tik stotys modulis yra. Būtinai sukurti naują NEMOKAMAI StudioLite sąskaitą gauti visą patirtį",
"bootBoxSaveRemoteSrv": "Išsaugokite darbą prie nuotolinio serverio",
"bootBoxSave": "Sutaupyti",
"bootBoxSaveAndRestart": "Išsaugokite keitimus ir perkraukite stotys",
"bootBoxCancel": "Atšaukti",
"bootBoxOk": "Gerai",
"bootBoxNoStationSelected": "Nr pasirinktos stoties",
"bootBoxProblemSaving": "Problema taupymo",
"bootBoxLoginWithProCred": "Vartotojas su Pro įgaliojimai ..",
"bootBoxProblem": "Problema",
"bootBoxWrongUserOrPass": "Atsiprašome, bet vartotojo vardas ar slaptažodis neatitiko!!",
"bootBoxSureDeleteCampaign": "Ar tikrai norite ištrinti kampaniją?",
"bootBoxCantDeleteComp": "Jūs negalite trinti kampaniją, kuri priskiriama prie nuotolinio stoties, prašome kišti JT paskirti jį iš stočių Prieš išimdami kampaniją.",
"bootBoxSelectCompFirst": "Pirmiausia turite pasirinkti kampaniją spustelėdami Ypatybės piktogramą.",
"bootBoxSureRemoveTimeline": "Ar tikrai norite pašalinti laiko juostą?",
"bootBoxCantDeleteTimeline": "Nepavyko ištrinti paskutinį grafikas, prašome sukurti naują tvarkaraštį prieš išbraukiant šį vieną",
"bootBoxSelectResource": "Pasirinkite išteklių pirmas ir bandykite dar kartą",
"bootBoxSelectChannel": "Pirmiausia pasirinkite kanalą, kurį norite susieti su turtu",
"bootBoxAtLeastOneDiv": "jūs turite turėti bent vieną matomo ekrano padalijimą",
"bootBoxScreenDivPosReset": "Ekrano padalinimo pozicija iš naujo",
"confirmSteps": "Šie veiksmai vyks, prašome patvirtinti?",
"addNewTimelineButtonToolTip": "Pridėti naują grafikas",
"campaignName": "Pasirinkite kampanijos pavadinimą",
"channelProps": "kanalų rekvizitai",
"bootBoxSteps": "Stotis bus ištrintas, jūsų darbas bus išsaugotas serveryje ir jūsų nuotolinio stoties (SignagePlayer Išregistruota",
"supportedFiles": "(Palaikomi failai: FLV, mp4, jpg, png ir swf",
"applyDimensions": "taikomi matmenys",
"thickness": "storis",
"borderColor": "Rėmelio spalva",
"borderProperties": "pasienio savybės",
"sceneBgColor": "Scenos fone",
"addScene": "pridėti sceną",
"addItem": "įdęti prekęs",
"removeScene": "pašalinti sceną",
"removeItem": "pašalinti elementą",
"sceneBlockList": "Daiktai",
"redo": "perdaryti",
"undo": "anuliuoti",
"sceneZoomIn": "Priartinti",
"sceneZoomOut": "Tolinti",
"sceneZoomReset": "Normalus dydis",
"enterSceneWidth": "Scenos plotis",
"enterSceneHeight": "Scenos aukštis",
"enterSceneText": "Scenos pavadinimas",
"selectScene": "Scena",
"pushItemToTopButtonToolTip": "stumti elementą į viršų",
"pushItemToBottomButtonToolTip": "stumti elementą apačioje",
"getNextItemButtonToolTip": "gauti kitą elementą",
"bootBoxSceneRemove": "Ar tikrai norite ištrinti šią sceną?",
"bootBoxSceneMustSelectScene": "Pirmiausia turite pasirinkti arba pridėti sceną",
"bootBoxOldBrowser": "Geeesh ... Jūsų naršyklė dinozauras, naudokite naujausią versiją iš Google Chrome `,` Microsoft Internet Explorer `arba` Mozilla Firefox `, o mes pažadame jums bus nustebinti ...",
"bootBoxNoFlash": "`Adobe Flash`, turi būti sumontuotas taip, jūs galite gyventi peržiūrą",
"quickIntro": "greitas intro",
"campaignPreviewTooltip": "kampanija peržiūra",
"playPreview": "žaisti peržiūrą",
"stopPreview": "sustabdyti peržiūrą",
"exitPreview": "išeiti peržiūra",
"launch": "pradėti",
"stop": "sustabdyti",
"exit": "išeiti",
"preview": "Peržiūra",
"cut": "sumažinti",
"copy": "kopija",
"duplicate": "dublikatas",
"paste": "pasta",
"remove": "pašalinti",
"dark": "tamsus",
"light": "šviesa",
"theme": "tema",
"moveFirst": "pereiti prie pirmo",
"moveLast": "pereiti į paskutinį",
"pushTop": "stumti viršų",
"pushBottom": "stumti dugną",
"lockMovement": "užrakinti žingsnis",
"pollInterval": "stotis apklausa (sekundės",
"fullScreenPreview": "visą ekraną peržiūra",
"magneticGrid": "magnetinio tinklelis",
"appSettings": "app nustatymai",
"timelinePreview": "Peržiūra tvarkaraštis",
"duplicateScene": "dubliuoti sceną",
"backToCampaignsTooltip": "atgal į kampanijos",
"bootBoxDuplicateScene": "Ar tikrai norite padaryti šią sceną kopiją?",
"navInstallPanel": "Įrengti",
"installSignagePlayer": "Įdiekite Ženklų grotuvas",
"chooseVersion": "Pasirinkti, kuri versija SignagePlayer norėtumėte gauti",
"recDevice": "Mes rekomenduojame, kad jūs perkate savo prietaisą kaip ji optimizuota ženklų programinės įrangos. Ji taip pat turi įmontuotą laikrodžio šuo ir programinė įranga iš anksto įdiegta, todėl jums nereikės nieko atsisiųsti ne visi",
"playerPreInstall": "SignagePlayer iš anksto įdiegta",
"step1": "1 veiksmas:",
"step2": "2 žingsnis:",
"step3": "3 veiksmas:",
"step4": "4 veiksmas:",
"purchaseOne": "įsigyti vieną iš mūsų prietaisų:",
"regDevice": "užregistruoti įrenginį su jūsų naudotojo",
"remoteManage": "pradėti nuotolinio valdymo prietaisą nuo",
"screens": "ekranai",
"secApp": "dalis šios paraiškos",
"signageAndroid": "SignagePlayer `Android`",
"downloadAndroid": "parsisiųsti grotuvas iš `Google` play parduotuvėje:",
"orderNow": "užsisakykite dabar",
"download": "Parsisiųsti",
"signageWindows": "SignagePlayer Windows",
"downloadAIR": "parsisiųsti Adobe AIR `runtime:",
"downloadSignagePlayer": "atsisiųsti SignagePlayer AIR app:",
"downloadIOS": "parsisiųsti žaidėjas iš App Store:",
"signageIOS": "SignagePlayer iOS",
"signageMac": "SignagePlayer Mac",
"andPass": "ir slaptažodis",
"editLayout": "redaguoti išdėstymas",
"createAccount": "arba sukurti naują sąskaitą",
"noAutoPopup": "Negalima Auto laikiną langą",
"firstChannel": "Pirmasis kanalas",
"totalCloudStorage": "Bendras debesys saugykla",
"refresh": "Perkrauti duomenis",
"final": ""
}
