{
"campaign_wizard": "નવી ઝુંબેશ વિઝાર્ડ",
"campaign_remove": "દૂર",
"navCampaign": "ઝુંબેશ",
"navResources": "સાધનો",
"navStation": "સ્ટેશન",
"navScenes": "દ્રશ્યો",
"navSettings": "સેટિંગ્સ",
"navGoPro": "પ્રો જાઓ",
"navStudioPanel": "માટે",
"freeBrackets": "(મફત",
"onehundredFree": "100% મફત",
"nintynine": "$ 99 એક મહિના (સપાટ",
"navHelpPanel": "મદદ",
"navLogout": "લૉગઆઉટ",
"saveConfig": "સેવ કરો",
"editScreenLayout": "ફેરફાર કરો સ્ક્રીન લેઆઉટ",
"liveChat": "લાઈવ ચેટ",
"dashboard": "ડેશબોર્ડ",
"editScreenLayoutTitle": "સ્ક્રીન લેઆઉટ એડિટર",
"pushToTop": "ટોચ પર દબાણ",
"studioLite": "StudioLite",
"rememberMe": "મને યાદ રાખો",
"signin": "સાઇન ઇન કરો",
"haveNiceDay": "એક સરસ દિવસ છે :",
"selectCampaignName": "તમારા ઝુંબેશ નામ પસંદ કરો",
"screenOrientation": "તમારી સ્ક્રીન અભિગમ પસંદ કરો",
"screenResolution": "તમારી સ્ક્રીન રીઝોલ્યુશન પસંદ કરો",
"screenLayout": "તમારી સ્ક્રીન લેઆઉટ પસંદ કરો",
"noTimelineSelected": "પસંદગી કોઈ સમયરેખા",
"addContent": "સામગ્રી ઉમેરો",
"removeContent": "સામગ્રી દૂર કરો",
"contentToAdd": "ઉમેરવા માટે નવી સામગ્રી પસંદ કરો",
"components": "ઘટકો",
"resources": "સાધનો",
"scenes": "દ્રશ્યો",
"comingSoon": "ટૂંક સમયમાં આવી ...",
"pleaseWait": "કૃપા કરીને રાહ જુઓ",
"removeStation": "સ્ટેશન દૂર",
"noStation": "કોઈ SignagePlayer લોડ ...",
"rightPackage": "તમારા માટે યોગ્ય છે કે પેકેજ પસંદ કરો!",
"studioLiteFree": "StudioLite",
"simpleInterface": "ઈન્ટરફેસ વાપરવા માટે સરળ",
"campaignManager": "પ્રચાર મેનેજર",
"timelineManagement": "સમયરેખા મેનેજમેન્ટ",
"screenTemplates": "સ્ક્રીન નમૂનાઓ",
"screenEditor": "સ્ક્રીન સંપાદક",
"StationManager": "સ્ટેશન મેનેજર",
"supportComponents": "આધાર 10 ઘટકો",
"sceneEditor": "(આવતા સીન સંપાદક",
"filesVIF": "વીડિયો છબીઓ ફ્લેશ",
"tabletsPhones": "ગોળીઓ અને ફોન પર ચલાવો",
"openSourceGithub": "ઓપન સોર્સ (GitHub",
"youAreHere": "આપ અહિ છો",
"studioProFree": "StudioPro",
"higherLearningCurve": "ઉચ્ચ શિક્ષણ વળાંક",
"professionalEditor": "વ્યવસાયિક સંપાદક",
"channelManagement": "ચેનલ વ્યવસ્થાપન",
"schedulerSequencer": "શેડ્યૂલર / Sequencer",
"richSceneEditor": "શ્રીમંત દ્રશ્ય સંપાદક",
"supportMoreComponents": "વધુ ઘટકો આધાર",
"advanceStationManager": "એડવાન્સ સ્ટેશન મેનેજર",
"runDesktopWeb": "ડેસ્કટોપ અને વેબ પર કોઈ રન નોંધાયો નહીં",
"muchMore": "અને વધુ ...",
"convert": "કન્વર્ટ",
"enterprise": "એન્ટરપ્રાઇઝ",
"everythingFromLiteAndPro": "લાઇટ અને પ્રો બધું",
"whiteLabel": "વ્હાઇટ લેબલ / બ્રાન્ડિંગ",
"supportAllComponents": "બધા ઘટકો આધાર",
"transitions": "અનુવાદ / અસરો",
"multiUserManagement": "મલ્ટી વપરાશકર્તા વ્યવસ્થાપન",
"advertisingManager": "જાહેરાત મેનેજર",
"accessControl": "વપરાશ નિયંત્રણ",
"unlimitedCloudStorage": "અનલિમિટેડ વાદળ સંગ્રહ",
"phoneSupport": "ફોન આધાર",
"hardwareDiscounts": "હાર્ડવેર ડિસ્કાઉન્ટ",
"month": "મહિનો",
"subscribe": "સબ્સ્ક્રાઇબ",
"videoTutorial": "વિડીયો ટ્યુટોરીયલ - StudioLite વાપરવા વિશે વધુ જાણવા",
"watchNow": "હવે તે જુઓ",
"additionalLinks": "વધારાની કડીઓ",
"studioLitePage": "Studiolo પાનું",
"supportForum": "આધાર ફોરમ",
"liveChatSupport": "લાઈવ ચેટ / આધાર",
"openSource": "મુક્ત સ્રોત",
"webinar": "Webinar",
"faq": "પ્રશ્નો",
"knowledgeBase": "જ્ઞાન આધાર",
"selectNextChannel": "આગામી ચેનલ પસંદ કરો",
"logout": "લૉગઆઉટ",
"server": "સર્વર:",
"businessId": "વ્યાપાર આઈડી:",
"username": "વપરાશકર્તા નામ:",
"password": "પાસવર્ડ",
"lenght": "લંબાઈ",
"randPlay": "રેન્ડમ પ્લેબૅક",
"off": "બંધ",
"on": "પર",
"resProps": "સ્ત્રોત મિલકત",
"screenDivision": "સ્ક્રીન વિભાગ",
"os": "ઓએસ",
"airVersion": "AIR આવૃત્તિ",
"playerVersion": "પ્લેયર આવૃત્તિ",
"peakMemory": "પીક મેમરી",
"totalMemory": "કુલ મેમરી",
"running": "ચાલી રહેલ",
"watchdog": "Watchdog",
"lastUpd": "છેલ્લે upd",
"sendStationEvent": "સ્ટેશન ઘટના મોકલો",
"enterQRText": "QR લખાણ દાખલ કરો",
"hoursMinutesSeconds": "કલાક / મિનિટ / સેકન્ડ",
"comp": "કોમ્પ",
"style": "શૈલી",
"aspectRatio": "સાપેક્ષ ગુણોત્તર",
"volumeLevel": "વોલ્યુંમ સ્તર",
"autoRewind": "ઓટો રીવાઇન્ડ",
"rssNewsSource": "આરએસએસ સમાચાર સ્રોત",
"rssRefreash": "આરએસએસ તાજું ટાઈમર (મિનિટ",
"rsscroll": "આરએસએસ સ્ક્રોલ દિશા",
"horizontalMode": "આડું સ્થિતિ",
"verticalMode": "વર્ટિકલ સ્થિતિ",
"scrollSpeed": "સરક ઝડપ",
"slow": "ધીમો",
"medium": "મધ્યમ",
"fast": "ઝડપી",
"font": "ફોન્ટ",
"maintainAR": "પાસા રેશિયો જાળવો",
"webAddr": "વેબ સરનામું",
"urlAddr": "URL અથવા સરનામું",
"labelText": "લેબલ લખાણ",
"chooseFormat": "બંધારણ પસંદ કરો",
"showBgColor": "પૃષ્ઠભૂમિ રંગ",
"ModalTitle": "મોડલ શીર્ષક",
"someContent": "કેટલીક સામગ્રી",
"close": "બંધ",
"saveChanges": "સુયોજનો સંગ્રહો",
"aboutUs": "અમારા વિશે",
"firstName": "પ્રથમ નામ",
"lastName": "છેલ્લું નામ",
"top": "ટોચ",
"left": "ડાબી",
"width": "પહોળાઈ",
"height": "ઊંચાઈ",
"angle": "કોણ",
"enterNewCompaignName": "નવી compaign નામ દાખલ કરો",
"timelineTitle": "સમયરેખા શીર્ષક",
"enterResName": "સ્ત્રોત નામ દાખલ કરો",
"eventName": "ઘટના નામ",
"EnterRSSLink": "આરએસએસ લિંક ટેક્સ્ટ દાખલ કરો",
"enterText": "અહીં લખાણ દાખલ કરો",
"removeTimelineButtonToolTip": "પસંદ કરેલ સમયરેખા દૂર (એક અસ્તિત્વમાં હોવું જોઈએ",
"addButtonToolTip": "add3",
"removeButtonToolTip": "વિભાગ દૂર",
"pushDivToTopButtonToolTip": "ટોચ પર વિભાગ દબાણ",
"pushDivToBottomButtonToolTip": "નીચે વિભાગ દબાણ",
"getNextDivButtonToolTip": "આગામી વિભાગ વિષે",
"unregRemoteStationButtonToolTip": "દૂરસ્થ સ્ટેશન unregisters",
"bootBoxThemeReload": "ફેરફારોની અસર લાવવા માટે તમે StudioLite પુન: શરૂ કરવાની જરૂર પડી શકે",
"bootBoxRestartStations": "જોડાયેલ સ્ટેશન પુન: શરૂ કરો અને તમારા બધા સેવ કામ લાગુ?",
"bootBoxStudioLiteAcc": "તમે StudioLite એકાઉન્ટ અને એ પ્રો એકાઉન્ટ સાથે પ્રવેશ જ જોઈએ",
"bootBoxLoginWrongCred": "તમે તેથી માત્ર સ્ટેશનો મોડ્યુલ ઉપલબ્ધ છે મફત SignageStudio પ્રો પ્રમાણપત્રો અને મફત નથી StudioLite ઓળખાણપત્ર સાથે લોગ થાય છે. સંપૂર્ણ અનુભવ મેળવવા માટે એક નવી મફત StudioLite એકાઉન્ટ બનાવવા માટે ખાતરી કરો",
"bootBoxSaveRemoteSrv": "દૂરસ્થ સર્વર પર કામ સાચવો",
"bootBoxSave": "સેવ કરો",
"bootBoxSaveAndRestart": "સાચવો અને સ્ટેશનો પુન: શરૂ કરો",
"bootBoxCancel": "રદ કરો",
"bootBoxOk": "બરાબર",
"bootBoxNoStationSelected": "પસંદગી ના સ્ટેશન",
"bootBoxProblemSaving": "સમસ્યા બચત",
"bootBoxLoginWithProCred": "પ્રો ઓળખાણપત્ર સાથે પ્રવેશ ..",
"bootBoxProblem": "સમસ્યા",
"bootBoxWrongUserOrPass": "માફ કરશો, પરંતુ વપરાશકર્તા અથવા પાસવર્ડ સાથે મેળ ખાતી નથી??",
"bootBoxSureDeleteCampaign": "શું તમે ખરેખર આ અભિયાન કાઢી નાખવા માંગો છો?",
"bootBoxCantDeleteComp": "તમે દૂરસ્થ સ્ટેશન સોંપેલ એક અભિયાન કે કાઢી શકતા નથી, તો તમે આ અભિયાન દૂર પહેલાં સ્ટેશનના તે વિરોધી સોંપી મૂક્કો કરો.",
"bootBoxSelectCompFirst": "તમે પ્રથમ ગુણધર્મો ચિહ્ન પર ક્લિક કરીને એક અભિયાન પસંદ કરવો આવશ્યક છે.",
"bootBoxSureRemoveTimeline": "શું તમે ખરેખર સમયરેખા દૂર કરવા માંગો છો?",
"bootBoxCantDeleteTimeline": "છેલ્લા સમયરેખા કાઢી શકાતું નથી, આ એક કાઢવા પહેલાં નવી ટાઈમલાઈન બનાવવા કરો",
"bootBoxSelectResource": "પ્રથમ સાધનની પસંદ કરો અને ફરીથી પ્રયાસ કરો",
"bootBoxSelectChannel": "પ્રથમ સાથે એસેટ સાંકળવા માટે ચેનલ પસંદ કરો",
"bootBoxAtLeastOneDiv": "તમે ઓછામાં ઓછું એક જોઈ શકાય સ્ક્રીન વિભાગ રાખવા જ જોઈએ",
"bootBoxScreenDivPosReset": "સ્ક્રીન વિભાગ સ્થિતિ રીસેટ",
"bootBoxCostumeTitle": "કસ્ટમ શીર્ષક",
"bootBoxContinue": "ચાલુ રાખો",
"confirmSteps": "નીચેના પગલાંઓ લેશે, ખાતરી કરો?",
"addNewTimelineButtonToolTip": "નવી સમયરેખા ઉમેરો",
"campaignName": "એક અભિયાન નામ પસંદ કરો",
"channelProps": "ચેનલ પ્રોપ્સ",
"bootBoxSteps": "સ્ટેશન કાઢી નાખવામાં આવશે, તમારા કામ સર્વર અને તમારા દૂરસ્થ સ્ટેશન (SignagePlayer દ-રજીસ્ટર કરવા માટે સાચવવામાં આવશે",
"supportedFiles": "(આધારભૂત ફાઈલો: એફએલવી, એમપી 4, JPG, PNG અને એસડબલ્યુએફ",
"applyDimensions": "પરિમાણો અરજી",
"thickness": "જાડાઈ",
"borderColor": "બોર્ડર રંગ",
"borderProperties": "સરહદ ગુણધર્મો",
"sceneBgColor": "દૃશ્ય પૃષ્ઠભૂમિ",
"addScene": "દ્રશ્ય ઉમેરો",
"addItem": "આઇટમ ઉમેરો",
"removeScene": "દ્રશ્ય દૂર",
"removeItem": "આઇટમ દૂર",
"sceneBlockList": "વસ્તુઓ",
"redo": "ફરી",
"undo": "પૂર્વવત્",
"sceneZoomIn": "ઝૂમ ઘટાડો",
"sceneZoomOut": "ઝૂમ ઘટાડો",
"sceneZoomReset": "ઝૂમ ફરીથી સેટ",
"enterSceneWidth": "દૃશ્ય પહોળાઈ",
"enterSceneHeight": "દૃશ્ય ઊંચાઈ",
"enterSceneText": "દૃશ્ય નામ",
"selectScene": "દૃશ્ય",
"pushItemToTopButtonToolTip": "ટોચ પર વસ્તુ દબાણ",
"pushItemToBottomButtonToolTip": "નીચે વસ્તુ દબાણ",
"getNextItemButtonToolTip": "આગામી વસ્તુ મળી",
"bootBoxSceneRemove": "શું તમે ખરેખર આ દ્રશ્ય દૂર કરવા માંગો છો?",
"bootBoxSceneMustSelectScene": "તમે પ્રથમ પસંદ અથવા દ્રશ્ય ઉમેરવું જ જોઈએ",
"bootBoxOldBrowser": "Geeesh ... તમારું બ્રાઉઝર Google Chrome, માઇક્રોસોફ્ટ ઇન્ટરનેટ એક્સ્પ્લોરર અથવા મોઝિલા ફાયરફોક્સ ના તાજેતરની આવૃત્તિ ઉપયોગ કરો, એક ડાયનાસોર છે, અને અમે તમને દંગ આવશે વચન ...",
"bootBoxNoFlash": "તમે પૂર્વાવલોકન રહી શકે છે, તેથી એડોબ ફ્લેશ સ્થાપિત હોવું જ જોઈએ",
"quickIntro": "ઝડપી પ્રસ્તાવના",
"campaignPreviewTooltip": "ઝુંબેશ પૂર્વાવલોકન",
"playPreview": "પૂર્વાવલોકન રમવા",
"stopPreview": "પૂર્વાવલોકન બંધ",
"exitPreview": "બહાર નીકળો પૂર્વાવલોકન",
"launch": "લોન્ચ",
"stop": "બંધ",
"exit": "બહાર નીકળો",
"preview": "પૂર્વદર્શન",
"cut": "કટ",
"copy": "નકલ",
"duplicate": "ડુપ્લિકેટ",
"paste": "પેસ્ટ",
"remove": "દૂર",
"dark": "શ્યામ",
"light": "પ્રકાશ",
"theme": "વિષય",
"moveFirst": "પ્રથમ ખસેડવા",
"moveLast": "છેલ્લા ખસેડવા",
"pushTop": "ટોચના દબાણ",
"pushBottom": "નીચે દબાણ",
"lockMovement": "ચાલ લોક",
"pollInterval": "સ્ટેશન મતદાન (સેકન્ડ",
"fullScreenPreview": "પૂર્ણ સ્ક્રીન પૂર્વાવલોકન",
"magneticGrid": "ચુંબકીય ગ્રીડ",
"appSettings": "એપ્લિકેશન સેટિંગ્સ",
"timelinePreview": "પૂર્વદર્શન સમયરેખા",
"duplicateScene": "દ્રશ્ય ડુપ્લિકેટ",
"backToCampaignsTooltip": "પાછા ઝુંબેશ માટે",
"bootBoxDuplicateScene": "શું તમે ખરેખર આ દ્રશ્ય એક નકલ બનાવવા માંગો છો?",
"navInstallPanel": "સ્થાપિત",
"installSignagePlayer": "એવી નિશાની પ્લેયર ઇન્સ્ટોલ કરો",
"chooseVersion": "તમે વિચાર કરવા માંગો છો SignagePlayer કયા આવૃત્તિ પસંદ કરો",
"recDevice": "અમે તે એવી નિશાની સોફ્ટવેર માટે શ્રેષ્ટ થયેલ છે કે તમે અમારા ઉપકરણ ખરીદી ભલામણ કરીએ છીએ. તે પણ એક ઘડિયાળ કૂતરું માં બનાવવામાં અને સોફ્ટવેર પૂર્વ સ્થાપિત આવે છે, જેથી તમે બધા કંઈપણ ડાઉનલોડ કરવાની આવશ્યકતા નથી",
"playerPreInstall": "SignagePlayer પૂર્વ સ્થાપિત",
"step1": "પગલું 1:",
"step2": "પગલું 2:",
"step3": "પગલું 3:",
"step4": "પગલું 4:",
"purchaseOne": "અમારા ઉપકરણો ખરીદી:",
"regDevice": "તમારા વપરાશકર્તા સાથે ઉપકરણને રજીસ્ટર",
"remoteManage": "દૂરસ્થ તમારા ઉપકરણ વ્યવસ્થા શરૂ",
"screens": "સ્ક્રીનો",
"secApp": "આ કાર્યક્રમની વિભાગ",
"signageAndroid": "Android માટે SignagePlayer",
"downloadAndroid": "ગૂગલ પ્લે સ્ટોર પરથી પ્લેયર ડાઉનલોડ:",
"orderNow": "માટે હવે",
"download": "ડાઉનલોડ",
"signageWindows": "Windows માટે SignagePlayer",
"downloadAIR": "એડોબ એરના રનટાઈમ ડાઉનલોડ:",
"downloadSignagePlayer": "પાંચ SignagePlayer AIR એપ્લિકેશન ડાઉનલોડ:",
"downloadIOS": "એપ સ્ટોર માંથી પ્લેયર ડાઉનલોડ:",
"signageIOS": "IOS માટે SignagePlayer",
"signageMac": "મેક માટે SignagePlayer",
"andPass": "અને પાસવર્ડ",
"editLayout": "ફેરફાર કરો લેઆઉટ",
"createAccount": "કે નવું એકાઉન્ટ બનાવો",
"noAutoPopup": "નથી ઓટો પોપઅપ કરો",
"final": ""
}
