{
"campaign_wizard": "nova kampanjo sorcxisto",
"campaign_remove": "forigi",
"navCampaign": "Kampanjo",
"navResources": "Rimedoj",
"navStation": "Stacioj",
"navScenes": "Scenoj",
"navSettings": "Agordoj",
"navGoPro": "Eniru Avantaĝo",
"navStudioPanel": "Ĉar",
"freeBrackets": "(LIBERA",
"onehundredFree": "100% LIBERA",
"nintynine": "$ 99 monate (ebena",
"navHelpPanel": "Helpu",
"navLogout": "Elsaluti",
"saveConfig": "Konservi",
"editScreenLayout": "redaktu ekrano aranĝo",
"liveChat": "Live babilejon",
"dashboard": "Panelo",
"editScreenLayoutTitle": "ekrano aranĝo redaktilon",
"pushToTop": "Puŝo supren",
"studioLite": "StudioLite",
"rememberMe": "Memoru min",
"signin": "Eniri",
"haveNiceDay": "Havu belan tagon :",
"selectCampaignName": "Elektu vian kampanjon nomo",
"screenOrientation": "Elektu vian ekranon orientiĝo",
"screenResolution": "Elektu vian ekranon distingivo",
"screenLayout": "Elektu vian ekranon aranĝo",
"noTimelineSelected": "neniu templinio selektitaj",
"addContent": "Aldoni enhavon",
"removeContent": "Forigi enhavon",
"contentToAdd": "Elektu novan enhavon aldoni",
"components": "komponantoj",
"resources": "rimedoj",
"scenes": "scenoj",
"comingSoon": "baldaŭ ...",
"pleaseWait": "Bonvolu atendi",
"removeStation": "forigi stacidomo",
"noStation": "Neniu SignagePlayer ŝarĝita ...",
"rightPackage": "Elektu la pakon kiu pravas pri vi!",
"studioLiteFree": "StudioLite",
"simpleInterface": "simpla uzi interfacon",
"campaignManager": "Kampanjo direktisto",
"timelineManagement": "Kronologio mastrumado",
"screenTemplates": "Ekrano ŝablonoj",
"screenEditor": "Ekrano redaktoro",
"StationManager": "Stacidomo Administranto",
"supportComponents": "Subtenu 10 komponantoj",
"sceneEditor": "Sceno redaktoro (venos",
"filesVIF": "videoj bildoj fulmilo",
"tabletsPhones": "Kuri sur Tablets kaj poŝtelefonoj",
"openSourceGithub": "Apertfonta (GitHub",
"youAreHere": "Vi estas ĉi tie",
"studioProFree": "StudioPro",
"higherLearningCurve": "Disertacion kurbo",
"professionalEditor": "Profesia redaktoro",
"channelManagement": "Kanalo demarŝo",
"schedulerSequencer": "Vicigilo / secuenciador",
"richSceneEditor": "Riĉaj sceno redaktilon",
"supportMoreComponents": "Subtenu pli komponantoj",
"advanceStationManager": "Advance Stacio Administranto",
"runDesktopWeb": "Regenta sur Labortablo kaj retejo",
"muchMore": "kaj multe pli ...",
"convert": "Konverti",
"enterprise": "Enterprise",
"everythingFromLiteAndPro": "Ĉion de Lite and Avantaĝo",
"whiteLabel": "Blanka label / brulmarko",
"supportAllComponents": "Subtenu ĉiuj komponantoj",
"transitions": "Transiroj / Efektoj",
"multiUserManagement": "Multi uzanto demarŝo",
"advertisingManager": "Reklamado direktisto",
"accessControl": "Aliro kontrolo",
"unlimitedCloudStorage": "Senlima nubo stokado",
"phoneSupport": "Telefono subteno",
"hardwareDiscounts": "Aparataro rabatoj",
"month": "monato",
"subscribe": "Aboni",
"videoTutorial": "Video lernilo - lerni kiel uzi StudioLite",
"watchNow": "Spektu ĝin nun",
"additionalLinks": "aldona ligiloj",
"studioLitePage": "Studiolo paĝo",
"supportForum": "Subteno forumo",
"liveChatSupport": "Live Babilejo / Subteno",
"openSource": "Apertfonta",
"webinar": "Webinar",
"faq": "FAQs",
"knowledgeBase": "Scio bazo",
"selectNextChannel": "selektu apud kanalo",
"logout": "Elsaluti",
"server": "Servilo:",
"businessId": "Komerco id:",
"username": "Vikipediista nomo:",
"password": "Pasvorto",
"lenght": "Daŭro",
"randPlay": "Hazarda Playback",
"off": "ekstere",
"on": "pri",
"resProps": "rimedo propraĵoj",
"screenDivision": "ekrano divido",
"os": "VIN",
"airVersion": "AIR versio",
"playerVersion": "Ludanto versio",
"peakMemory": "Peak memoro",
"totalMemory": "Entutaj memoro",
"running": "Ruli",
"watchdog": "Gardisto",
"lastUpd": "Lasta upd",
"sendStationEvent": "Sendu stacidomo okazaĵo",
"enterQRText": "QR Entajpu Teksto",
"hoursMinutesSeconds": "horoj / minutoj / sekundoj",
"comp": "Comp",
"style": "Stilo",
"aspectRatio": "Aspekto rilatumo",
"volumeLevel": "Volumo nivelo",
"autoRewind": "Aŭto Rewind",
"rssNewsSource": "RSS-novaĵojn vikitekston",
"rssRefreash": "RSS refresh timer (minutoj",
"rsscroll": "RSS skribrulaĵon direkto",
"horizontalMode": "Horizontala modo",
"verticalMode": "Vertikala modo",
"scrollSpeed": "Scroll rapido",
"slow": "Malrapida",
"medium": "Meza",
"fast": "Rapida",
"font": "Tiparo",
"maintainAR": "Subteni aspekto rilatumo",
"webAddr": "Ttt-adreso",
"urlAddr": "URL adreso",
"labelText": "Label teksto",
"chooseFormat": "Elektu formaton",
"showBgColor": "fonkoloro",
"ModalTitle": "Modala titolo",
"someContent": "iu enhavo",
"close": "Fermi",
"saveChanges": "Konservi ŝanĝojn",
"aboutUs": "Pri ni",
"firstName": "Antaŭnomo",
"lastName": "Familinomo",
"top": "supro",
"left": "maldekstra",
"width": "larĝeco",
"height": "alteco",
"angle": "angulo",
"enterNewCompaignName": "Entajpu novan compaign nomo",
"timelineTitle": "Kronologio Titolo",
"enterResName": "Entajpu rimedo nomo",
"eventName": "okazaĵo nomo",
"EnterRSSLink": "Entajpu RSS ligilo teksto",
"enterText": "Entajpu Teksto Jen",
"removeTimelineButtonToolTip": "forigi la elektitan timeline (oni devas ekzisti",
"addButtonToolTip": "add3",
"removeButtonToolTip": "forigi divido",
"pushDivToTopButtonToolTip": "puŝi divido supren",
"pushDivToBottomButtonToolTip": "puŝi divido al malsupro",
"getNextDivButtonToolTip": "get proksima divido",
"unregRemoteStationButtonToolTip": "unregisters fora stacidomo",
"bootBoxThemeReload": "Vi eble bezonas restartigi StudioLite ŝanĝojn preni efikon",
"bootBoxRestartStations": "Restartigu konektita stacidomoj kaj apliku vian tutan savis laboro?",
"bootBoxStudioLiteAcc": "Vi devas ensaluti per StudioLite konto kaj ne Avantaĝo konton",
"bootBoxLoginWrongCred": "Vi ensalutis kun LIBERA SignageStudio Avantaĝo akrediton kaj ne LIBERA StudioLite akreditaĵojn do nur la stacioj modulo estas havebla. Estu certa ke por krei novan LIBERA StudioLite konton por ricevi la plenan sperto",
"bootBoxSaveRemoteSrv": "Konservu la verkon al fora servilo",
"bootBoxSave": "Konservi",
"bootBoxSaveAndRestart": "Konservi kaj rekomencos stacioj",
"bootBoxCancel": "Nuligi",
"bootBoxOk": "OK",
"bootBoxNoStationSelected": "Neniu stacidomo selektitaj",
"bootBoxProblemSaving": "Problemo ŝparante",
"bootBoxLoginWithProCred": "Ensalutu kun Avantaĝo akreditaĵojn ..",
"bootBoxProblem": "Problemo",
"bootBoxWrongUserOrPass": "Pardonon sed la uzanto aŭ pasvorto ne kongruas?!?!",
"bootBoxSureDeleteCampaign": "Ĉu vi certas ke vi volas forviŝi la kampanjo?",
"bootBoxCantDeleteComp": "Vi ne povas forviŝi la kampanjo kiu estas atribuita al fora stacidomo, bonvole pugno un-atribui ĝin el Stacioj antaux vi forigas la kampanjo.",
"bootBoxSelectCompFirst": "Vi devas unue elekti kampanjon per klako sur la ecojn ikono.",
"bootBoxSureRemoveTimeline": "Ĉu vi certas ke vi volas forigi la templinio?",
"bootBoxCantDeleteTimeline": "Ne eblas forigi la lastan tempolinio, bonvolu krei novan templinio antaux viŝi ĉi tiu",
"bootBoxSelectResource": "Bonvolu elekti rimedon unua kaj reprovu",
"bootBoxSelectChannel": "Bonvolu unue elekti kanalo asocii aktivo kun",
"bootBoxAtLeastOneDiv": "vi devas konservi almenaŭ unu viewable ekrano divido",
"bootBoxScreenDivPosReset": "ekrano divido pozicio reset",
"bootBoxCostumeTitle": "Propra titolo",
"bootBoxContinue": "Daŭri",
"confirmSteps": "La sekvaj paŝoj okazos, bonvolu konfirmi?",
"addNewTimelineButtonToolTip": "Aldoni novan templinio",
"campaignName": "Elektu kampanjo nomo",
"channelProps": "kanalo tornapuntas",
"bootBoxSteps": "Stacidomo estos forigita, via laboro estos savita al la servilo kaj via fora stacidomo (SignagePlayer de-registrita",
"supportedFiles": "(Apogita dosieroj: flv, MP4, jpg, png kaj SWF",
"applyDimensions": "apliki dimensioj",
"thickness": "dikeco",
"borderColor": "limo koloro",
"borderProperties": "limo propraĵoj",
"sceneBgColor": "Sceno fono",
"addScene": "aldoni sceno",
"addItem": "aldoni listero",
"removeScene": "forigi sceno",
"removeItem": "forigi eron",
"sceneBlockList": "Items",
"redo": "refari",
"undo": "undo",
"sceneZoomIn": "Zomi",
"sceneZoomOut": "Malzomi",
"sceneZoomReset": "Zoom reset",
"enterSceneWidth": "Sceno larĝa",
"enterSceneHeight": "Sceno alteco",
"enterSceneText": "Sceno nomo",
"selectScene": "Sceno",
"pushItemToTopButtonToolTip": "puŝi eron supren",
"pushItemToBottomButtonToolTip": "puŝi eron al malsupro",
"getNextItemButtonToolTip": "get proksima listero",
"bootBoxSceneRemove": "Ĉu vi certas ke vi volas forigi ĉi tiun scenon?",
"bootBoxSceneMustSelectScene": "Vi devas unue elekti aŭ aldonu sceno",
"bootBoxOldBrowser": "Geeesh ... Via foliumilo estas dinosaŭro, bonvole uzu la lastan version de Google Chrome, Microsoft Internet Explorer aŭ Mozilla Firefox, kaj ni promesas al vi estos mirigitaj ...",
"bootBoxNoFlash": "Adobe Flash devas esti instalita por ke vi povu vivi antaŭvido",
"quickIntro": "rapida enkonduko al",
"campaignPreviewTooltip": "kampanjo antaŭvido",
"playPreview": "ludi antaŭvido",
"stopPreview": "halti antaŭvido",
"exitPreview": "eliro antaŭvido",
"launch": "ĵeto",
"stop": "halti",
"exit": "eliro",
"preview": "antaŭvido",
"cut": "tranĉo",
"copy": "Kopio",
"duplicate": "duobligi",
"paste": "pasto",
"remove": "forigi",
"dark": "malhela",
"light": "lumo",
"theme": "temo",
"moveFirst": "movi al la unua",
"moveLast": "movi al lasta",
"pushTop": "puŝi supro",
"pushBottom": "puŝi malsupro",
"lockMovement": "ŝlosi movado",
"pollInterval": "stacidomo polling (sekundoj",
"fullScreenPreview": "plena ekrano antaŭvido",
"magneticGrid": "magneta krado",
"appSettings": "app agordojn",
"timelinePreview": "Preview templinio",
"duplicateScene": "duobligi sceno",
"backToCampaignsTooltip": "reen al kampanjoj",
"bootBoxDuplicateScene": "ĉu vi certas ke vi volas fari kopion de ĉi tiu sceno?",
"navInstallPanel": "Instali",
"installSignagePlayer": "Instalu la ŝildoj Ludanto",
"chooseVersion": "Elektu kiun version de SignagePlayer vi ŝatus ricevi",
"recDevice": "Ni rekomendas ke vi aĉetas nia mekanismo kiel estas optimumigita por la ŝildoj programaro. Ĝi havas ankaŭ konstruita en observejon hundo kaj la programaro venas antaŭ-instalita, do vi ne bezonas elŝuti ion ajn",
"playerPreInstall": "SignagePlayer antaŭ-instalita",
"step1": "Paŝo 1:",
"step2": "Paŝo 2:",
"step3": "Paŝo 3:",
"step4": "Paŝo 4:",
"purchaseOne": "aĉeti unu el niaj aparatoj:",
"regDevice": "aliĝu al la aparato per via uzanto",
"remoteManage": "komenci fora administri vian aparaton de la",
"screens": "ekranoj",
"secApp": "sekcio de tiu apliko",
"signageAndroid": "SignagePlayer por Android",
"downloadAndroid": "elŝuti ludanto de Google teatraĵo vendejo:",
"orderNow": "Por nun",
"download": "malŝarĝo",
"signageWindows": "SignagePlayer por Vindozo",
"downloadAIR": "elŝuti Adobe AIR runtime:",
"downloadSignagePlayer": "elŝuti la SignagePlayer AIR app:",
"downloadIOS": "elŝuti ludanto de la App Store:",
"signageIOS": "SignagePlayer por IOS",
"signageMac": "SignagePlayer por Mac",
"andPass": "kaj pasvorto",
"editLayout": "redaktu aranĝo",
"createAccount": "aŭ krei novan konton",
"noAutoPopup": "ne auto-fenestron",
"final": ""
}
